codialog/__init__.py
codialog/app.py
codialog/templates/index.html
codialog/tests/test_basic.py
react/node_modules/flatted/python/flatted.py
react/node_modules/flatted/python/test.py
codialog-0.2.1.dist-info/METADATA
codialog-0.2.1.dist-info/WHEEL
codialog-0.2.1.dist-info/entry_points.txt
codialog-0.2.1.dist-info/top_level.txt
codialog-0.2.1.dist-info/RECORD
